README.rst
setup.py
plypatch/__init__.py
plypatch/cli.py
plypatch/exc.py
plypatch/fixup_patch.py
plypatch/utils.py
plypatch/version.py
plypatch/git/__init__.py
plypatch/git/exc.py
plypatch3.egg-info/PKG-INFO
plypatch3.egg-info/SOURCES.txt
plypatch3.egg-info/dependency_links.txt
plypatch3.egg-info/entry_points.txt
plypatch3.egg-info/top_level.txt