Metadata-Version: 1.1
Name: plypatch3
Version: 0.4.3
Summary: Ply: Git-based Patch Management
Home-page: https://github.com/sorrowless/ply
Author: Rick Harris, Stan Bogatkin
Author-email: rconradharris@gmail.com, stabog.tmb@gmail.com
License: MIT
Platform: UNKNOWN
Classifier: Development Status :: 4 - Beta
Classifier: License :: OSI Approved :: Apache Software License
Classifier: Operating System :: POSIX :: Linux
Classifier: Programming Language :: Python :: 2
Classifier: Programming Language :: Python :: 3
